{
    "alias": "manovotny.com",
    "name": "manovotny",
    "static": {
        "cleanUrls": true,
        "directoryListing": false,
        "headers": [
            {
                "headers": [
                    {
                        "key": "Cache-Control",
                        "value": "public, max-age=31536000, immutable"
                    }
                ],
                "source": "/**/*"
            }
        ],
        "renderSingle": true,
        "trailingSlash": false
    },
    "type": "static"
}
